primer_automate_client/__init__.py
primer_automate_client/__version__.py
primer_automate_client/automate_client.py
primer_automate_client-0.0.1.dist-info/METADATA
primer_automate_client-0.0.1.dist-info/WHEEL
primer_automate_client-0.0.1.dist-info/top_level.txt
primer_automate_client-0.0.1.dist-info/RECORD
